sdcli/__init__.py
sdcli/__main__.py
sdcli/config/__init__.py
sdcli/config/_config.py
sdcli/config/config_obs.py
sdcli/src/__init__.py
sdcli/src/cli.py
sdcli/src/lib/__init__.py
sdcli/src/lib/error.py
sdcli/src/lib/generator.py
sdcli/src/lib/info.py
sdcli-1.2.0.dist-info/LICENSE
sdcli-1.2.0.dist-info/METADATA
sdcli-1.2.0.dist-info/WHEEL
sdcli-1.2.0.dist-info/entry_points.txt
sdcli-1.2.0.dist-info/top_level.txt
sdcli-1.2.0.dist-info/RECORD
