Metadata-Version: 2.1
Name: sdcli
Version: 1.2.0
Summary: 
Home-page: UNKNOWN
Author: Jose Segura
Author-email: j0s3s3gur4@gmail.com
License: MIT
Project-URL: Code, https://github.com/DarkCode01/streamelopers-cli
Platform: linux
Platform: macos
Requires-Python: >=3.7
Requires-Dist: Click
Requires-Dist: colorama
